{
	"response": [
		{
			"maintainer": "xc112lg",
			"oem": "",
			"device": "",
			"filename": "crDroidAndroid-14.0-20240318-h872-v10.2.zip",
			"download": "https://github.com/xc112lg/crdroid10.x/releases/download/crDroidAndroid-14.0-20240318/crDroidAndroid-14.0-20240318-h872-v10.2.zip",
			"timestamp": 1710762710,
			"md5": "3b93184e9022b5e9c8a594553c891d71",
			"sha256": "2d29d3840b765da2e2a3e8037380728ba8cca6123a20c280f7acf85cb372634e",
			"size": 1019038903,
			"version": "10.2",
			"buildtype": "",
			"forum": "",
			"gapps": "",
			"firmware": "",
			"modem": "",
			"bootloader": "",
			"recovery": "https://github.com/xc112lg/crdroid10.x/releases/tag/crDroidAndroid-14.0-20240305",
			"paypal": "https://www.paypal.com/paypalme/xc112xda",
			"telegram": "",
			"dt": "",
			"common-dt": "",
			"kernel": ""
		}
,
		{
			"maintainer": "xc112lg",
			"oem": "",
			"device": "",
			"filename": "crDroidAndroid-14.0-20240318-h872-v10.2.zip",
			"download": "https://github.com/xc112lg/crdroid10.x/releases/download/crDroidAndroid-14.0-20240318/crDroidAndroid-14.0-20240318-h872-v10.2.zip",
			"timestamp": 1710762710,
			"md5": "3b93184e9022b5e9c8a594553c891d71",
			"sha256": "2d29d3840b765da2e2a3e8037380728ba8cca6123a20c280f7acf85cb372634e",
			"size": 1019038903,
			"version": "10.2",
			"buildtype": "",
			"forum": "",
			"gapps": "",
			"firmware": "",
			"modem": "",
			"bootloader": "",
			"recovery": "https://github.com/xc112lg/crdroid10.x/releases/tag/crDroidAndroid-14.0-20240305",
			"paypal": "https://www.paypal.com/paypalme/xc112xda",
			"telegram": "",
			"dt": "",
			"common-dt": "",
			"kernel": ""
		}
,
		{
			"maintainer": "xc112lg",
			"oem": "",
			"device": "",
			"filename": "crDroidAndroid-14.0-20240318-h872-v10.2.zip",
			"download": "https://github.com/xc112lg/crdroid10.x/releases/download/crDroidAndroid-14.0-20240318/crDroidAndroid-14.0-20240318-h872-v10.2.zip",
			"timestamp": 1710762710,
			"md5": "3b93184e9022b5e9c8a594553c891d71",
			"sha256": "2d29d3840b765da2e2a3e8037380728ba8cca6123a20c280f7acf85cb372634e",
			"size": 1019038903,
			"version": "10.2",
			"buildtype": "",
			"forum": "",
			"gapps": "",
			"firmware": "",
			"modem": "",
			"bootloader": "",
			"recovery": "https://github.com/xc112lg/crdroid10.x/releases/tag/crDroidAndroid-14.0-20240305",
			"paypal": "https://www.paypal.com/paypalme/xc112xda",
			"telegram": "",
			"dt": "",
			"common-dt": "",
			"kernel": ""
		}
,
		{
			"maintainer": "xc112lg",
			"oem": "",
			"device": "",
			"filename": "crDroidAndroid-14.0-20240318-h872-v10.2.zip",
			"download": "https://github.com/xc112lg/crdroid10.x/releases/download/crDroidAndroid-14.0-20240318/crDroidAndroid-14.0-20240318-h872-v10.2.zip",
			"timestamp": 1710762710,
			"md5": "3b93184e9022b5e9c8a594553c891d71",
			"sha256": "2d29d3840b765da2e2a3e8037380728ba8cca6123a20c280f7acf85cb372634e",
			"size": 1019038903,
			"version": "10.2",
			"buildtype": "",
			"forum": "",
			"gapps": "",
			"firmware": "",
			"modem": "",
			"bootloader": "",
			"recovery": "https://github.com/xc112lg/crdroid10.x/releases/tag/crDroidAndroid-14.0-20240305",
			"paypal": "https://www.paypal.com/paypalme/xc112xda",
			"telegram": "",
			"dt": "",
			"common-dt": "",
			"kernel": ""
		}
,
		{
			"maintainer": "xc112lg",
			"oem": "",
			"device": "",
			"filename": "crDroidAndroid-14.0-20240318-h872-v10.2.zip",
			"download": "https://github.com/xc112lg/crdroid10.x/releases/download/crDroidAndroid-14.0-20240318/crDroidAndroid-14.0-20240318-h872-v10.2.zip",
			"timestamp": 1710762710,
			"md5": "3b93184e9022b5e9c8a594553c891d71",
			"sha256": "2d29d3840b765da2e2a3e8037380728ba8cca6123a20c280f7acf85cb372634e",
			"size": 1019038903,
			"version": "10.2",
			"buildtype": "",
			"forum": "",
			"gapps": "",
			"firmware": "",
			"modem": "",
			"bootloader": "",
			"recovery": "https://github.com/xc112lg/crdroid10.x/releases/tag/crDroidAndroid-14.0-20240305",
			"paypal": "https://www.paypal.com/paypalme/xc112xda",
			"telegram": "",
			"dt": "",
			"common-dt": "",
			"kernel": ""
		}
,
		{
			"maintainer": "xc112lg",
			"oem": "",
			"device": "",
			"filename": "crDroidAndroid-14.0-20240318-h872-v10.2.zip",
			"download": "https://github.com/xc112lg/crdroid10.x/releases/download/crDroidAndroid-14.0-20240318/crDroidAndroid-14.0-20240318-h872-v10.2.zip",
			"timestamp": 1710762710,
			"md5": "3b93184e9022b5e9c8a594553c891d71",
			"sha256": "2d29d3840b765da2e2a3e8037380728ba8cca6123a20c280f7acf85cb372634e",
			"size": 1019038903,
			"version": "10.2",
			"buildtype": "",
			"forum": "",
			"gapps": "",
			"firmware": "",
			"modem": "",
			"bootloader": "",
			"recovery": "https://github.com/xc112lg/crdroid10.x/releases/tag/crDroidAndroid-14.0-20240305",
			"paypal": "https://www.paypal.com/paypalme/xc112xda",
			"telegram": "",
			"dt": "",
			"common-dt": "",
			"kernel": ""
		}
,
		{
			"maintainer": "xc112lg",
			"oem": "",
			"device": "",
			"filename": "crDroidAndroid-14.0-20240318-h872-v10.2.zip",
			"download": "https://github.com/xc112lg/crdroid10.x/releases/download/crDroidAndroid-14.0-20240318/crDroidAndroid-14.0-20240318-h872-v10.2.zip",
			"timestamp": 1710762710,
			"md5": "3b93184e9022b5e9c8a594553c891d71",
			"sha256": "2d29d3840b765da2e2a3e8037380728ba8cca6123a20c280f7acf85cb372634e",
			"size": 1019038903,
			"version": "10.2",
			"buildtype": "",
			"forum": "",
			"gapps": "",
			"firmware": "",
			"modem": "",
			"bootloader": "",
			"recovery": "https://github.com/xc112lg/crdroid10.x/releases/tag/crDroidAndroid-14.0-20240305",
			"paypal": "https://www.paypal.com/paypalme/xc112xda",
			"telegram": "",
			"dt": "",
			"common-dt": "",
			"kernel": ""
		}
,
		{
			"maintainer": "xc112lg",
			"oem": "",
			"device": "",
			"filename": "crDroidAndroid-14.0-20240318-h872-v10.2.zip",
			"download": "https://github.com/xc112lg/crdroid10.x/releases/download/crDroidAndroid-14.0-20240318/crDroidAndroid-14.0-20240318-h872-v10.2.zip",
			"timestamp": 1710762710,
			"md5": "3b93184e9022b5e9c8a594553c891d71",
			"sha256": "2d29d3840b765da2e2a3e8037380728ba8cca6123a20c280f7acf85cb372634e",
			"size": 1019038903,
			"version": "10.2",
			"buildtype": "",
			"forum": "",
			"gapps": "",
			"firmware": "",
			"modem": "",
			"bootloader": "",
			"recovery": "https://github.com/xc112lg/crdroid10.x/releases/tag/crDroidAndroid-14.0-20240305",
			"paypal": "https://www.paypal.com/paypalme/xc112xda",
			"telegram": "",
			"dt": "",
			"common-dt": "",
			"kernel": ""
		}
,
		{
			"maintainer": "xc112lg",
			"oem": "",
			"device": "",
			"filename": "crDroidAndroid-14.0-20240318-h872-v10.2.zip",
			"download": "https://github.com/xc112lg/crdroid10.x/releases/download/crDroidAndroid-14.0-20240318/crDroidAndroid-14.0-20240318-h872-v10.2.zip",
			"timestamp": 1710762710,
			"md5": "3b93184e9022b5e9c8a594553c891d71",
			"sha256": "2d29d3840b765da2e2a3e8037380728ba8cca6123a20c280f7acf85cb372634e",
			"size": 1019038903,
			"version": "10.2",
			"buildtype": "",
			"forum": "",
			"gapps": "",
			"firmware": "",
			"modem": "",
			"bootloader": "",
			"recovery": "https://github.com/xc112lg/crdroid10.x/releases/tag/crDroidAndroid-14.0-20240305",
			"paypal": "https://www.paypal.com/paypalme/xc112xda",
			"telegram": "",
			"dt": "",
			"common-dt": "",
			"kernel": ""
		}
,
		{
			"maintainer": "xc112lg",
			"oem": "",
			"device": "",
			"filename": "crDroidAndroid-14.0-20240318-h872-v10.2.zip",
			"download": "https://github.com/xc112lg/crdroid10.x/releases/download/crDroidAndroid-14.0-20240318/crDroidAndroid-14.0-20240318-h872-v10.2.zip",
			"timestamp": 1710762710,
			"md5": "3b93184e9022b5e9c8a594553c891d71",
			"sha256": "2d29d3840b765da2e2a3e8037380728ba8cca6123a20c280f7acf85cb372634e",
			"size": 1019038903,
			"version": "10.2",
			"buildtype": "",
			"forum": "",
			"gapps": "",
			"firmware": "",
			"modem": "",
			"bootloader": "",
			"recovery": "https://github.com/xc112lg/crdroid10.x/releases/tag/crDroidAndroid-14.0-20240305",
			"paypal": "https://www.paypal.com/paypalme/xc112xda",
			"telegram": "",
			"dt": "",
			"common-dt": "",
			"kernel": ""
		}
,
		{
			"maintainer": "xc112lg",
			"oem": "",
			"device": "",
			"filename": "crDroidAndroid-14.0-20240318-h872-v10.2.zip",
			"download": "https://github.com/xc112lg/crdroid10.x/releases/download/crDroidAndroid-14.0-20240318/crDroidAndroid-14.0-20240318-h872-v10.2.zip",
			"timestamp": 1710762710,
			"md5": "3b93184e9022b5e9c8a594553c891d71",
			"sha256": "2d29d3840b765da2e2a3e8037380728ba8cca6123a20c280f7acf85cb372634e",
			"size": 1019038903,
			"version": "10.2",
			"buildtype": "",
			"forum": "",
			"gapps": "",
			"firmware": "",
			"modem": "",
			"bootloader": "",
			"recovery": "https://github.com/xc112lg/crdroid10.x/releases/tag/crDroidAndroid-14.0-20240305",
			"paypal": "https://www.paypal.com/paypalme/xc112xda",
			"telegram": "",
			"dt": "",
			"common-dt": "",
			"kernel": ""
		}
,
		{
			"maintainer": "xc112lg",
			"oem": "",
			"device": "",
			"filename": "crDroidAndroid-14.0-20240318-h872-v10.2.zip",
			"download": "https://github.com/xc112lg/crdroid10.x/releases/download/crDroidAndroid-14.0-20240318/crDroidAndroid-14.0-20240318-h872-v10.2.zip",
			"timestamp": 1710762710,
			"md5": "3b93184e9022b5e9c8a594553c891d71",
			"sha256": "2d29d3840b765da2e2a3e8037380728ba8cca6123a20c280f7acf85cb372634e",
			"size": 1019038903,
			"version": "10.2",
			"buildtype": "",
			"forum": "",
			"gapps": "",
			"firmware": "",
			"modem": "",
			"bootloader": "",
			"recovery": "https://github.com/xc112lg/crdroid10.x/releases/tag/crDroidAndroid-14.0-20240305",
			"paypal": "https://www.paypal.com/paypalme/xc112xda",
			"telegram": "",
			"dt": "",
			"common-dt": "",
			"kernel": ""
		}
,
		{
			"maintainer": "xc112lg",
			"oem": "",
			"device": "",
			"filename": "crDroidAndroid-14.0-20240318-h872-v10.2.zip",
			"download": "https://github.com/xc112lg/crdroid10.x/releases/download/crDroidAndroid-14.0-20240318/crDroidAndroid-14.0-20240318-h872-v10.2.zip",
			"timestamp": 1710762710,
			"md5": "3b93184e9022b5e9c8a594553c891d71",
			"sha256": "2d29d3840b765da2e2a3e8037380728ba8cca6123a20c280f7acf85cb372634e",
			"size": 1019038903,
			"version": "10.2",
			"buildtype": "",
			"forum": "",
			"gapps": "",
			"firmware": "",
			"modem": "",
			"bootloader": "",
			"recovery": "https://github.com/xc112lg/crdroid10.x/releases/tag/crDroidAndroid-14.0-20240305",
			"paypal": "https://www.paypal.com/paypalme/xc112xda",
			"telegram": "",
			"dt": "",
			"common-dt": "",
			"kernel": ""
		}
,
		{
			"maintainer": "xc112lg",
			"oem": "",
			"device": "",
			"filename": "crDroidAndroid-14.0-20240312-h872-v10.2.zip",
			"download": "https://github.com/xc112lg/crdroid10.x/releases/download/crDroidAndroid-14.0-20240312/crDroidAndroid-14.0-20240312-h872-v10.2.zip",
			"timestamp": 1710220655,
			"md5": "937d45df1ddd121353cc18854b09970d",
			"sha256": "7c9bd0304d3f1759695af1b9f76bb2a40cd9db777c178bf5ba97f92c4d02c5ee",
			"size": 1019197585,
			"version": "10.2",
			"buildtype": "",
			"forum": "",
			"gapps": "",
			"firmware": "",
			"modem": "",
			"bootloader": "",
			"recovery": "https://github.com/xc112lg/crdroid10.x/releases/tag/crDroidAndroid-14.0-20240305",
			"paypal": "https://www.paypal.com/paypalme/xc112xda",
			"telegram": "",
			"dt": "",
			"common-dt": "",
			"kernel": ""
		}
,
		{
			"maintainer": "xc112lg",
			"oem": "",
			"device": "",
			"filename": "crDroidAndroid-14.0-20240312-h872-v10.2.zip",
			"download": "https://github.com/xc112lg/crdroid10.x/releases/download/crDroidAndroid-14.0-20240312/crDroidAndroid-14.0-20240312-h872-v10.2.zip",
			"timestamp": 1710220655,
			"md5": "937d45df1ddd121353cc18854b09970d",
			"sha256": "7c9bd0304d3f1759695af1b9f76bb2a40cd9db777c178bf5ba97f92c4d02c5ee",
			"size": 1019197585,
			"version": "10.2",
			"buildtype": "",
			"forum": "",
			"gapps": "",
			"firmware": "",
			"modem": "",
			"bootloader": "",
			"recovery": "https://github.com/xc112lg/crdroid10.x/releases/tag/crDroidAndroid-14.0-20240305",
			"paypal": "https://www.paypal.com/paypalme/xc112xda",
			"telegram": "",
			"dt": "",
			"common-dt": "",
			"kernel": ""
		}
,
		{
			"maintainer": "xc112lg",
			"oem": "",
			"device": "",
			"filename": "crDroidAndroid-14.0-20240308-h872-v10.2.zip",
			"download": "https://github.com/xc112lg/crdroid10.x/releases/download/crDroidAndroid-14.0-20240308/crDroidAndroid-14.0-20240308-h872-v10.2.zip",
			"timestamp": 1709872572,
			"md5": "3b956177c0897f3778846564eef1afd7",
			"sha256": "b8c887b89ad8b0f8608cf8a754614fcab5adb3af7e4b4815b42ac402e07f7cc9",
			"size": 1012296773,
			"version": "10.2",
			"buildtype": "",
			"forum": "",
			"gapps": "",
			"firmware": "",
			"modem": "",
			"bootloader": "",
			"recovery": "https://github.com/xc112lg/crdroid10.x/releases/tag/crDroidAndroid-14.0-20240305",
			"paypal": "https://www.paypal.com/paypalme/xc112xda",
			"telegram": "",
			"dt": "",
			"common-dt": "",
			"kernel": ""
		}
	]
}
